dxh_py/VERSION.txt
dxh_py/__init__.py
dxh_py/__main__.py
dxh_py/cli.py
dxh_py/config.py
dxh_py/environment.py
dxh_py/exceptions.py
dxh_py/extensions.py
dxh_py/find.py
dxh_py/generate.py
dxh_py/hooks.py
dxh_py/log.py
dxh_py/main.py
dxh_py/prompt.py
dxh_py/replay.py
dxh_py/repository.py
dxh_py/utils.py
dxh_py/vcs.py
dxh_py/zipfile.py
dxh_py-0.0.5.dist-info/LICENSE.md
dxh_py-0.0.5.dist-info/METADATA
dxh_py-0.0.5.dist-info/WHEEL
dxh_py-0.0.5.dist-info/entry_points.txt
dxh_py-0.0.5.dist-info/top_level.txt
dxh_py-0.0.5.dist-info/RECORD
